tractor/SampleBridges
tractor/__init__.py
tractor/actions.py
tractor/bridges.py
tractor/checks.py
tractor/control.py
tractor/db.py
tractor/proxy.py
tractor/tractor.gschema.xml
tractor/tractor.py
tractor/tractorrc.py
traxtor-5.1.0.dist-info/entry_points.txt
traxtor-5.1.0.dist-info/licenses/LICENSE
traxtor-5.1.0.dist-info/WHEEL
traxtor-5.1.0.dist-info/METADATA
traxtor-5.1.0.dist-info/RECORD
