Metadata-Version: 2.4
Name: traxtor
Version: 5.1.0
Summary: Setup an onion routing proxy
Keywords: Tor,onion,stem
Author-email: Danial Behzadi <dani.behzi@ubuntu.com>
Requires-Python: >=3.9
Classifier: Programming Language :: Python :: 3
Classifier: License :: OSI Approved :: GNU General Public License v3 or later (GPLv3+)
Classifier: Operating System :: OS Independent
License-File: LICENSE
Requires-Dist: PyGObject
Requires-Dist: fire
Requires-Dist: pysocks
Requires-Dist: stem
Project-URL: Bug Tracker, https://framagit.org/tractor/tractor/-/issues
Project-URL: Documentation, https://framagit.org/tractor/tractor/-/blob/main/tractor/man/tractor.1
Project-URL: Homepage, https://tractor.frama.io/tractor
Project-URL: Source Code, https://framagit.org/tractor/tractor
